setup.cfg
setup.py
asched/__init__.py
asched/events.py
asched/job.py
asched/util.py
asched.egg-info/PKG-INFO
asched.egg-info/SOURCES.txt
asched.egg-info/dependency_links.txt
asched.egg-info/entry_points.txt
asched.egg-info/requires.txt
asched.egg-info/top_level.txt
asched/executors/__init__.py
asched/executors/asyncio.py
asched/executors/base.py
asched/executors/base_py3.py
asched/executors/debug.py
asched/executors/pool.py
asched/jobstores/__init__.py
asched/jobstores/base.py
asched/jobstores/memory.py
asched/schedulers/__init__.py
asched/schedulers/asyncio.py
asched/schedulers/background.py
asched/schedulers/base.py
asched/schedulers/blocking.py
asched/triggers/__init__.py
asched/triggers/base.py
asched/triggers/combining.py
asched/triggers/date.py
asched/triggers/interval.py
asched/triggers/cron/__init__.py
asched/triggers/cron/expressions.py
asched/triggers/cron/fields.py