Metadata-Version: 1.0
Name: asched
Version: 1.2.0
Summary: asyncio sched
Home-page: UNKNOWN
Author: UNKNOWN
Author-email: UNKNOWN
License: MIT
Platform: UNKNOWN
